runcheap_ssg/__init__.py
runcheap_ssg/decorators.py
runcheap_ssg/management/__init__.py
runcheap_ssg/management/commands/__init__.py
runcheap_ssg/management/commands/runcheap_ssg_build.py
runcheap_ssg/management/commands/runcheap_ssg_serve.py
runcheap_ssg/templatetags/__init__.py
runcheap_ssg/templatetags/runcheap_ssg.py
runcheap_ssg-1.0.3.dist-info/licenses/LICENSE
runcheap_ssg-1.0.3.dist-info/METADATA
runcheap_ssg-1.0.3.dist-info/WHEEL
runcheap_ssg-1.0.3.dist-info/top_level.txt
runcheap_ssg-1.0.3.dist-info/RECORD
