Metadata-Version: 2.4
Name: runcheap-ssg
Version: 1.0.3
Summary: A static site generator app for django
Author-email: Daniel Roesler <daniel@run.cheap>
Maintainer-email: Daniel Roesler <daniel@run.cheap>
License-Expression: AGPL-3.0-or-later
Project-URL: Homepage, https://github.com/runcheap/runcheap-ssg
Project-URL: Documentation, https://github.com/runcheap/runcheap-ssg
Project-URL: Repository, https://github.com/runcheap/runcheap-ssg
Project-URL: Bug Tracker, https://github.com/runcheap/runcheap-ssg/issues
Classifier: Development Status :: 4 - Beta
Classifier: Intended Audience :: Developers
Classifier: Operating System :: OS Independent
Classifier: Framework :: Django
Classifier: Programming Language :: Python
Requires-Python: >=3.10
License-File: LICENSE
Requires-Dist: django>=4.2.11
Provides-Extra: dev
Requires-Dist: black; extra == "dev"
Requires-Dist: flake8; extra == "dev"
Dynamic: license-file
